MANIFEST.in
README.md
setup.cfg
setup.py
examples/apiserver/apiserver_aiohttp.py
examples/apiserver/apiserver_flask.py
examples/apiserver/requirements.txt
src/floodgateio/__init__.py
src/floodgateio/consts.py
src/floodgateio/floodgate_client.py
src/floodgateio/floodgate_client_async.py
src/floodgateio/floodgate_client_base.py
src/floodgateio/version.py
src/floodgateio/configurations/__init__.py
src/floodgateio/configurations/client_config_async.py
src/floodgateio/configurations/client_config_base.py
src/floodgateio/configurations/client_config_sync.py
src/floodgateio/configurations/client_config_with_autoupdate.py
src/floodgateio/configurations/client_config_with_autoupdate_async.py
src/floodgateio/evaluators/__init__.py
src/floodgateio/evaluators/evaluator_helper.py
src/floodgateio/evaluators/rollout_evaluator.py
src/floodgateio/evaluators/target_evaluator.py
src/floodgateio/store/__init__.py
src/floodgateio/store/cache.py
src/floodgateio/types/__init__.py
src/floodgateio/types/exceptions.py
src/floodgateio/types/feature_flag_entity.py
src/floodgateio/types/rollout_entity.py
src/floodgateio/types/rule_entity.py
src/floodgateio/types/target_entity.py
src/floodgateio/types/user.py
src/floodgateio/utils/__init__.py
src/floodgateio/utils/converter.py
src/floodgateio/utils/http_resource_fetcher.py
src/floodgateio/utils/http_resource_fetcher_aiohttp.py
src/floodgateio/utils/http_resource_fetcher_requests.py
src/floodgateio_python.egg-info/PKG-INFO
src/floodgateio_python.egg-info/SOURCES.txt
src/floodgateio_python.egg-info/dependency_links.txt
src/floodgateio_python.egg-info/requires.txt
src/floodgateio_python.egg-info/top_level.txt