Metadata-Version: 2.1
Name: floodgateio-python
Version: 0.0.11
Summary: floodgate.io python client
Home-page: https://github.com/densolo/floodgateio-python
Author: denissolo
License: MIT
Platform: UNKNOWN
Classifier: Programming Language :: Python :: 3
Classifier: License :: OSI Approved :: MIT License
Classifier: Operating System :: OS Independent
Requires-Python: >=3.6
